LICENSE.txt
README.rst
setup.py
bottle_jwt2/__init__.py
bottle_jwt2/auth.py
bottle_jwt2/backends.py
bottle_jwt2/compat.py
bottle_jwt2/error.py
bottle_jwt2.egg-info/PKG-INFO
bottle_jwt2.egg-info/SOURCES.txt
bottle_jwt2.egg-info/dependency_links.txt
bottle_jwt2.egg-info/requires.txt
bottle_jwt2.egg-info/top_level.txt
test/test_bottle_jwt.py